odoo/addons/account_invoice_report_hide_discounts_by_partner/README.rst
odoo/addons/account_invoice_report_hide_discounts_by_partner/__init__.py
odoo/addons/account_invoice_report_hide_discounts_by_partner/__manifest__.py
odoo/addons/account_invoice_report_hide_discounts_by_partner/data/data.xml
odoo/addons/account_invoice_report_hide_discounts_by_partner/i18n/ca_ES.po
odoo/addons/account_invoice_report_hide_discounts_by_partner/i18n/es.po
odoo/addons/account_invoice_report_hide_discounts_by_partner/migrations/16.0.1.0.1/pre-migration.py
odoo/addons/account_invoice_report_hide_discounts_by_partner/models/__init__.py
odoo/addons/account_invoice_report_hide_discounts_by_partner/models/account_move.py
odoo/addons/account_invoice_report_hide_discounts_by_partner/models/res_partner.py
odoo/addons/account_invoice_report_hide_discounts_by_partner/reports/report_invoice.xml
odoo/addons/account_invoice_report_hide_discounts_by_partner/static/description/icon.png
odoo/addons/account_invoice_report_hide_discounts_by_partner/tests/__init__.py
odoo/addons/account_invoice_report_hide_discounts_by_partner/tests/test_hide_discounts_by_partner.py
odoo/addons/account_invoice_report_hide_discounts_by_partner/views/account_move_views.xml
odoo/addons/account_invoice_report_hide_discounts_by_partner/views/res_partner_views.xml
odoo_addon_account_invoice_report_hide_discounts_by_partner-16.0.1.2.0.dist-info/METADATA
odoo_addon_account_invoice_report_hide_discounts_by_partner-16.0.1.2.0.dist-info/WHEEL
odoo_addon_account_invoice_report_hide_discounts_by_partner-16.0.1.2.0.dist-info/top_level.txt
odoo_addon_account_invoice_report_hide_discounts_by_partner-16.0.1.2.0.dist-info/RECORD
