Metadata-Version: 2.1
Name: odoo-addon-account_invoice_report_hide_discounts_by_partner
Version: 16.0.1.2.0
Summary: Account Invoice Report Hide Discounts by Partner
Home-page: https://github.com/sygel-technology/sy-account-invoice-reporting
Author: Sygel, Odoo Community Association (OCA)
Author-email: support@odoo-community.org
License: AGPL-3
Classifier: Programming Language :: Python
Classifier: Framework :: Odoo
Classifier: Framework :: Odoo :: 16.0
Classifier: License :: OSI Approved :: GNU Affero General Public License v3
Requires-Python: >=3.10
Requires-Dist: odoo<16.1dev,>=16.0a
